README.md
setup.py
WOPkg/__init__.py
WOPkg/main.py
WOPkg.egg-info/PKG-INFO
WOPkg.egg-info/SOURCES.txt
WOPkg.egg-info/dependency_links.txt
WOPkg.egg-info/not-zip-safe
WOPkg.egg-info/top_level.txt
wopkg/main.py